Metadata-Version: 2.4
Name: rf-faiss
Version: 1.13.0
Summary: A library for efficient similarity search and clustering of dense vectors
Home-page: https://github.com/facebookresearch/faiss
Author: Matthijs Douze, Jeff Johnson, Herve Jegou, Lucas Hosseini
Author-email: faiss@meta.com
License: MIT
Keywords: search nearest neighbors
Requires-Dist: numpy
Requires-Dist: packaging
Dynamic: author
Dynamic: author-email
Dynamic: description
Dynamic: description-content-type
Dynamic: home-page
Dynamic: keywords
Dynamic: license
Dynamic: requires-dist
Dynamic: summary
